design.sv
// ============================================================
// UART TX/RX IP CORE
// 8-bit data, 1 start bit, 1 stop bit, no parity (8-N-1)
// ============================================================

module uart_tx #(
    parameter CLKS_PER_BIT = 10
)(
    input        clk,
    input        rst,
    input        tx_start,
    input  [7:0] tx_data,
    output reg   tx,
    output reg   tx_busy
);

    reg [2:0]  bit_count;
    reg [7:0]  data_reg;
    reg [15:0] clk_count;

    localparam IDLE  = 2'b00;
    localparam START = 2'b01;
    localparam DATA  = 2'b10;
    localparam STOP  = 2'b11;

    reg [1:0] state;

    always @(posedge clk) begin
        if (rst) begin
            state     <= IDLE;
            tx        <= 1'b1;
            tx_busy   <= 1'b0;
            bit_count <= 0;
            clk_count <= 0;
            data_reg  <= 0;
        end
        else begin
            case (state)
                IDLE: begin
                    tx <= 1'b1;
                    tx_busy <= 1'b0;
                    clk_count <= 0;
                    if (tx_start) begin
                        data_reg <= tx_data;
                        tx_busy <= 1'b1;
                        tx <= 1'b0;
                        bit_count <= 0;
                        state <= START;
                    end
                end

                START: begin
                    if (clk_count == CLKS_PER_BIT-1) begin
                        clk_count <= 0;
                        state <= DATA;
                        tx <= data_reg[0];
                    end
                    else clk_count <= clk_count + 1;
                end

                DATA: begin
                    if (clk_count == CLKS_PER_BIT-1) begin
                        clk_count <= 0;
                        if (bit_count == 7) begin
                            state <= STOP;
                            tx <= 1'b1;
                        end
                        else begin
                            bit_count <= bit_count + 1;
                            tx <= data_reg[bit_count + 1];
                        end
                    end
                    else clk_count <= clk_count + 1;
                end

                STOP: begin
                    if (clk_count == CLKS_PER_BIT-1) begin
                        clk_count <= 0;
                        state <= IDLE;
                        tx <= 1'b1;
                        tx_busy <= 1'b0;
                    end
                    else clk_count <= clk_count + 1;
                end
            endcase
        end
    end
endmodule


module uart_rx #(
    parameter CLKS_PER_BIT = 10
)(
    input        clk,
    input        rst,
    input        rx,
    output reg [7:0] rx_data,
    output reg       rx_valid
);

    reg [15:0] clk_count;
    reg [2:0]  bit_count;
    reg [7:0]  data_reg;

    localparam RX_IDLE  = 2'b00;
    localparam RX_START = 2'b01;
    localparam RX_DATA  = 2'b10;
    localparam RX_STOP  = 2'b11;

    reg [1:0] state;

    always @(posedge clk) begin
        if (rst) begin
            state <= RX_IDLE;
            clk_count <= 0;
            bit_count <= 0;
            data_reg <= 0;
            rx_data <= 0;
            rx_valid <= 0;
        end
        else begin
            rx_valid <= 1'b0;

            case (state)
                RX_IDLE: begin
                    clk_count <= 0;
                    bit_count <= 0;
                    if (rx == 1'b0) state <= RX_START;
                end

                RX_START: begin
                    if (clk_count == (CLKS_PER_BIT/2)-1) begin
                        if (rx == 1'b0) begin
                            clk_count <= 0;
                            state <= RX_DATA;
                        end
                        else state <= RX_IDLE;
                    end
                    else clk_count <= clk_count + 1;
                end

                RX_DATA: begin
                    if (clk_count == CLKS_PER_BIT-1) begin
                        clk_count <= 0;
                        data_reg[bit_count] <= rx;
                        if (bit_count == 7) begin
                            bit_count <= 0;
                            state <= RX_STOP;
                        end
                        else bit_count <= bit_count + 1;
                    end
                    else clk_count <= clk_count + 1;
                end

                RX_STOP: begin
                    if (clk_count == CLKS_PER_BIT-1) begin
                        clk_count <= 0;
                        if (rx == 1'b1) begin
                            rx_data <= data_reg;
                            rx_valid <= 1'b1;
                        end
                        state <= RX_IDLE;
                    end
                    else clk_count <= clk_count + 1;
                end
            endcase
        end
    end
endmodule

testbench.sv
module testbench;

reg clk;
reg rst;
reg tx_start;
reg [7:0] tx_data;

wire tx;
wire tx_busy;
wire [7:0] rx_data;
wire rx_valid;

uart_tx #(.CLKS_PER_BIT(10)) transmitter (
    .clk(clk),
    .rst(rst),
    .tx_start(tx_start),
    .tx_data(tx_data),
    .tx(tx),
    .tx_busy(tx_busy)
);

uart_rx #(.CLKS_PER_BIT(10)) receiver (
    .clk(clk),
    .rst(rst),
    .rx(tx),
    .rx_data(rx_data),
    .rx_valid(rx_valid)
);

always #5 clk = ~clk;

initial begin
    $dumpfile("uart.vcd");
    $dumpvars(0, testbench);

    clk = 0;
    rst = 1;
    tx_start = 0;
    tx_data = 0;

    #20;
    rst = 0;

    // Test 1
    tx_data = 8'hA5;
    tx_start = 1;
    #10;
    tx_start = 0;
    #1100;

    // Test 2
    tx_data = 8'h3C;
    tx_start = 1;
    #10;
    tx_start = 0;
    #1100;

    $finish;
end

always @(posedge rx_valid) begin
    $display("UART RECEIVED: 0x%h (%d)", rx_data, rx_data);
end

endmodule

uart.vcd
$version Generated by VerilatedVcd $end
$timescale 1ns $end
 $scope module testbench $end
  $var wire 1 / clk $end
  $var wire 1 0 rst $end
  $var wire 1 1 tx_start $end
  $var wire 8 2 tx_data [7:0] $end
  $var wire 1 # tx $end
  $var wire 1 $ tx_busy $end
  $var wire 8 % rx_data [7:0] $end
  $var wire 1 & rx_valid $end
  $scope module receiver $end
   $var wire 32 3 CLKS_PER_BIT [31:0] $end
   $var wire 1 / clk $end
   $var wire 1 0 rst $end
   $var wire 1 # rx $end
   $var wire 8 % rx_data [7:0] $end
   $var wire 1 & rx_valid $end
   $var wire 16 ' clk_count [15:0] $end
   $var wire 3 ( bit_count [2:0] $end
   $var wire 8 ) data_reg [7:0] $end
   $var wire 2 4 RX_IDLE [1:0] $end
   $var wire 2 5 RX_START [1:0] $end
   $var wire 2 6 RX_DATA [1:0] $end
   $var wire 2 7 RX_STOP [1:0] $end
   $var wire 2 * state [1:0] $end
  $upscope $end
  $scope module transmitter $end
   $var wire 32 3 CLKS_PER_BIT [31:0] $end
   $var wire 1 / clk $end
   $var wire 1 0 rst $end
   $var wire 1 1 tx_start $end
   $var wire 8 2 tx_data [7:0] $end
   $var wire 1 # tx $end
   $var wire 1 $ tx_busy $end
   $var wire 3 + bit_count [2:0] $end
   $var wire 8 , data_reg [7:0] $end
   $var wire 16 - clk_count [15:0] $end
   $var wire 2 4 IDLE [1:0] $end
   $var wire 2 5 START [1:0] $end
   $var wire 2 6 DATA [1:0] $end
   $var wire 2 7 STOP [1:0] $end
   $var wire 2 . state [1:0] $end
  $upscope $end
 $upscope $end
$enddefinitions $end


#0
0#
0$
b00000000 %
0&
b0000000000000000 '
b000 (
b00000000 )
b00 *
b000 +
b00000000 ,
b0000000000000000 -
b00 .
0/
10
01
b00000000 2
b00000000000000000000000000001010 3
b00 4
b01 5
b10 6
b11 7
#5
1#
1/
#10
0/
#15
1/
#20
0/
00
11
b10100101 2
#25
0#
1$
b10100101 ,
b01 .
1/
#30
0/
01
#35
b01 *
b0000000000000001 -
1/
#40
0/
#45
b0000000000000001 '
b0000000000000010 -
1/
#50
0/
#55
b0000000000000010 '
b0000000000000011 -
1/
#60
0/
#65
b0000000000000011 '
b0000000000000100 -
1/
#70
0/
#75
b0000000000000100 '
b0000000000000101 -
1/
#80
0/
#85
b0000000000000000 '
b10 *
b0000000000000110 -
1/
#90
0/
#95
b0000000000000001 '
b0000000000000111 -
1/
#100
0/
#105
b0000000000000010 '
b0000000000001000 -
1/
#110
0/
#115
b0000000000000011 '
b0000000000001001 -
1/
#120
0/
#125
1#
b0000000000000100 '
b0000000000000000 -
b10 .
1/
#130
0/
#135
b0000000000000101 '
b0000000000000001 -
1/
#140
0/
#145
b0000000000000110 '
b0000000000000010 -
1/
#150
0/
#155
b0000000000000111 '
b0000000000000011 -
1/
#160
0/
#165
b0000000000001000 '
b0000000000000100 -
1/
#170
0/
#175
b0000000000001001 '
b0000000000000101 -
1/
#180
0/
#185
b0000000000000000 '
b001 (
b00000001 )
b0000000000000110 -
1/
#190
0/
#195
b0000000000000001 '
b0000000000000111 -
1/
#200
0/
#205
b0000000000000010 '
b0000000000001000 -
1/
#210
0/
#215
b0000000000000011 '
b0000000000001001 -
1/
#220
0/
#225
0#
b0000000000000100 '
b001 +
b0000000000000000 -
1/
#230
0/
#235
b0000000000000101 '
b0000000000000001 -
1/
#240
0/
#245
b0000000000000110 '
b0000000000000010 -
1/
#250
0/
#255
b0000000000000111 '
b0000000000000011 -
1/
#260
0/
#265
b0000000000001000 '
b0000000000000100 -
1/
#270
0/
#275
b0000000000001001 '
b0000000000000101 -
1/
#280
0/
#285
b0000000000000000 '
b010 (
b0000000000000110 -
1/
#290
0/
#295
b0000000000000001 '
b0000000000000111 -
1/
#300
0/
#305
b0000000000000010 '
b0000000000001000 -
1/
#310
0/
#315
b0000000000000011 '
b0000000000001001 -
1/
#320
0/
#325
1#
b0000000000000100 '
b010 +
b0000000000000000 -
1/
#330
0/
#335
b0000000000000101 '
b0000000000000001 -
1/
#340
0/
#345
b0000000000000110 '
b0000000000000010 -
1/
#350
0/
#355
b0000000000000111 '
b0000000000000011 -
1/
#360
0/
#365
b0000000000001000 '
b0000000000000100 -
1/
#370
0/
#375
b0000000000001001 '
b0000000000000101 -
1/
#380
0/
#385
b0000000000000000 '
b011 (
b00000101 )
b0000000000000110 -
1/
#390
0/
#395
b0000000000000001 '
b0000000000000111 -
1/
#400
0/
#405
b0000000000000010 '
b0000000000001000 -
1/
#410
0/
#415
b0000000000000011 '
b0000000000001001 -
1/
#420
0/
#425
0#
b0000000000000100 '
b011 +
b0000000000000000 -
1/
#430
0/
#435
b0000000000000101 '
b0000000000000001 -
1/
#440
0/
#445
b0000000000000110 '
b0000000000000010 -
1/
#450
0/
#455
b0000000000000111 '
b0000000000000011 -
1/
#460
0/
#465
b0000000000001000 '
b0000000000000100 -
1/
#470
0/
#475
b0000000000001001 '
b0000000000000101 -
1/
#480
0/
#485
b0000000000000000 '
b100 (
b0000000000000110 -
1/
#490
0/
#495
b0000000000000001 '
b0000000000000111 -
1/
#500
0/
#505
b0000000000000010 '
b0000000000001000 -
1/
#510
0/
#515
b0000000000000011 '
b0000000000001001 -
1/
#520
0/
#525
b0000000000000100 '
b100 +
b0000000000000000 -
1/
#530
0/
#535
b0000000000000101 '
b0000000000000001 -
1/
#540
0/
#545
b0000000000000110 '
b0000000000000010 -
1/
#550
0/
#555
b0000000000000111 '
b0000000000000011 -
1/
#560
0/
#565
b0000000000001000 '
b0000000000000100 -
1/
#570
0/
#575
b0000000000001001 '
b0000000000000101 -
1/
#580
0/
#585
b0000000000000000 '
b101 (
b0000000000000110 -
1/
#590
0/
#595
b0000000000000001 '
b0000000000000111 -
1/
#600
0/
#605
b0000000000000010 '
b0000000000001000 -
1/
#610
0/
#615
b0000000000000011 '
b0000000000001001 -
1/
#620
0/
#625
1#
b0000000000000100 '
b101 +
b0000000000000000 -
1/
#630
0/
#635
b0000000000000101 '
b0000000000000001 -
1/
#640
0/
#645
b0000000000000110 '
b0000000000000010 -
1/
#650
0/
#655
b0000000000000111 '
b0000000000000011 -
1/
#660
0/
#665
b0000000000001000 '
b0000000000000100 -
1/
#670
0/
#675
b0000000000001001 '
b0000000000000101 -
1/
#680
0/
#685
b0000000000000000 '
b110 (
b00100101 )
b0000000000000110 -
1/
#690
0/
#695
b0000000000000001 '
b0000000000000111 -
1/
#700
0/
#705
b0000000000000010 '
b0000000000001000 -
1/
#710
0/
#715
b0000000000000011 '
b0000000000001001 -
1/
#720
0/
#725
0#
b0000000000000100 '
b110 +
b0000000000000000 -
1/
#730
0/
#735
b0000000000000101 '
b0000000000000001 -
1/
#740
0/
#745
b0000000000000110 '
b0000000000000010 -
1/
#750
0/
#755
b0000000000000111 '
b0000000000000011 -
1/
#760
0/
#765
b0000000000001000 '
b0000000000000100 -
1/
#770
0/
#775
b0000000000001001 '
b0000000000000101 -
1/
#780
0/
#785
b0000000000000000 '
b111 (
b0000000000000110 -
1/
#790
0/
#795
b0000000000000001 '
b0000000000000111 -
1/
#800
0/
#805
b0000000000000010 '
b0000000000001000 -
1/
#810
0/
#815
b0000000000000011 '
b0000000000001001 -
1/
#820
0/
#825
1#
b0000000000000100 '
b111 +
b0000000000000000 -
1/
#830
0/
#835
b0000000000000101 '
b0000000000000001 -
1/
#840
0/
#845
b0000000000000110 '
b0000000000000010 -
1/
#850
0/
#855
b0000000000000111 '
b0000000000000011 -
1/
#860
0/
#865
b0000000000001000 '
b0000000000000100 -
1/
#870
0/
#875
b0000000000001001 '
b0000000000000101 -
1/
#880
0/
#885
b0000000000000000 '
b000 (
b10100101 )
b11 *
b0000000000000110 -
1/
#890
0/
#895
b0000000000000001 '
b0000000000000111 -
1/
#900
0/
#905
b0000000000000010 '
b0000000000001000 -
1/
#910
0/
#915
b0000000000000011 '
b0000000000001001 -
1/
#920
0/
#925
b0000000000000100 '
b0000000000000000 -
b11 .
1/
#930
0/
#935
b0000000000000101 '
b0000000000000001 -
1/
#940
0/
#945
b0000000000000110 '
b0000000000000010 -
1/
#950
0/
#955
b0000000000000111 '
b0000000000000011 -
1/
#960
0/
#965
b0000000000001000 '
b0000000000000100 -
1/
#970
0/
#975
b0000000000001001 '
b0000000000000101 -
1/
#980
0/
#985
b10100101 %
1&
b0000000000000000 '
b00 *
b0000000000000110 -
1/
#990
0/
#995
0&
b0000000000000111 -
1/
#1000
0/
#1005
b0000000000001000 -
1/
#1010
0/
#1015
b0000000000001001 -
1/
#1020
0/
#1025
0$
b0000000000000000 -
b00 .
1/
#1030
0/
#1035
1/
#1040
0/
#1045
1/
#1050
0/
#1055
1/
#1060
0/
#1065
1/
#1070
0/
#1075
1/
#1080
0/
#1085
1/
#1090
0/
#1095
1/
#1100
0/
#1105
1/
#1110
0/
#1115
1/
#1120
0/
#1125
1/
#1130
0/
11
b00111100 2
#1135
0#
1$
b000 +
b00111100 ,
b01 .
1/
#1140
0/
01
#1145
b01 *
b0000000000000001 -
1/
#1150
0/
#1155
b0000000000000001 '
b0000000000000010 -
1/
#1160
0/
#1165
b0000000000000010 '
b0000000000000011 -
1/
#1170
0/
#1175
b0000000000000011 '
b0000000000000100 -
1/
#1180
0/
#1185
b0000000000000100 '
b0000000000000101 -
1/
#1190
0/
#1195
b0000000000000000 '
b10 *
b0000000000000110 -
1/
#1200
0/
#1205
b0000000000000001 '
b0000000000000111 -
1/
#1210
0/
#1215
b0000000000000010 '
b0000000000001000 -
1/
#1220
0/
#1225
b0000000000000011 '
b0000000000001001 -
1/
#1230
0/
#1235
b0000000000000100 '
b0000000000000000 -
b10 .
1/
#1240
0/
#1245
b0000000000000101 '
b0000000000000001 -
1/
#1250
0/
#1255
b0000000000000110 '
b0000000000000010 -
1/
#1260
0/
#1265
b0000000000000111 '
b0000000000000011 -
1/
#1270
0/
#1275
b0000000000001000 '
b0000000000000100 -
1/
#1280
0/
#1285
b0000000000001001 '
b0000000000000101 -
1/
#1290
0/
#1295
b0000000000000000 '
b001 (
b10100100 )
b0000000000000110 -
1/
#1300
0/
#1305
b0000000000000001 '
b0000000000000111 -
1/
#1310
0/
#1315
b0000000000000010 '
b0000000000001000 -
1/
#1320
0/
#1325
b0000000000000011 '
b0000000000001001 -
1/
#1330
0/
#1335
b0000000000000100 '
b001 +
b0000000000000000 -
1/
#1340
0/
#1345
b0000000000000101 '
b0000000000000001 -
1/
#1350
0/
#1355
b0000000000000110 '
b0000000000000010 -
1/
#1360
0/
#1365
b0000000000000111 '
b0000000000000011 -
1/
#1370
0/
#1375
b0000000000001000 '
b0000000000000100 -
1/
#1380
0/
#1385
b0000000000001001 '
b0000000000000101 -
1/
#1390
0/
#1395
b0000000000000000 '
b010 (
b0000000000000110 -
1/
#1400
0/
#1405
b0000000000000001 '
b0000000000000111 -
1/
#1410
0/
#1415
b0000000000000010 '
b0000000000001000 -
1/
#1420
0/
#1425
b0000000000000011 '
b0000000000001001 -
1/
#1430
0/
#1435
1#
b0000000000000100 '
b010 +
b0000000000000000 -
1/
#1440
0/
#1445
b0000000000000101 '
b0000000000000001 -
1/
#1450
0/
#1455
b0000000000000110 '
b0000000000000010 -
1/
#1460
0/
#1465
b0000000000000111 '
b0000000000000011 -
1/
#1470
0/
#1475
b0000000000001000 '
b0000000000000100 -
1/
#1480
0/
#1485
b0000000000001001 '
b0000000000000101 -
1/
#1490
0/
#1495
b0000000000000000 '
b011 (
b0000000000000110 -
1/
#1500
0/
#1505
b0000000000000001 '
b0000000000000111 -
1/
#1510
0/
#1515
b0000000000000010 '
b0000000000001000 -
1/
#1520
0/
#1525
b0000000000000011 '
b0000000000001001 -
1/
#1530
0/
#1535
b0000000000000100 '
b011 +
b0000000000000000 -
1/
#1540
0/
#1545
b0000000000000101 '
b0000000000000001 -
1/
#1550
0/
#1555
b0000000000000110 '
b0000000000000010 -
1/
#1560
0/
#1565
b0000000000000111 '
b0000000000000011 -
1/
#1570
0/
#1575
b0000000000001000 '
b0000000000000100 -
1/
#1580
0/
#1585
b0000000000001001 '
b0000000000000101 -
1/
#1590
0/
#1595
b0000000000000000 '
b100 (
b10101100 )
b0000000000000110 -
1/
#1600
0/
#1605
b0000000000000001 '
b0000000000000111 -
1/
#1610
0/
#1615
b0000000000000010 '
b0000000000001000 -
1/
#1620
0/
#1625
b0000000000000011 '
b0000000000001001 -
1/
#1630
0/
#1635
b0000000000000100 '
b100 +
b0000000000000000 -
1/
#1640
0/
#1645
b0000000000000101 '
b0000000000000001 -
1/
#1650
0/
#1655
b0000000000000110 '
b0000000000000010 -
1/
#1660
0/
#1665
b0000000000000111 '
b0000000000000011 -
1/
#1670
0/
#1675
b0000000000001000 '
b0000000000000100 -
1/
#1680
0/
#1685
b0000000000001001 '
b0000000000000101 -
1/
#1690
0/
#1695
b0000000000000000 '
b101 (
b10111100 )
b0000000000000110 -
1/
#1700
0/
#1705
b0000000000000001 '
b0000000000000111 -
1/
#1710
0/
#1715
b0000000000000010 '
b0000000000001000 -
1/
#1720
0/
#1725
b0000000000000011 '
b0000000000001001 -
1/
#1730
0/
#1735
b0000000000000100 '
b101 +
b0000000000000000 -
1/
#1740
0/
#1745
b0000000000000101 '
b0000000000000001 -
1/
#1750
0/
#1755
b0000000000000110 '
b0000000000000010 -
1/
#1760
0/
#1765
b0000000000000111 '
b0000000000000011 -
1/
#1770
0/
#1775
b0000000000001000 '
b0000000000000100 -
1/
#1780
0/
#1785
b0000000000001001 '
b0000000000000101 -
1/
#1790
0/
#1795
b0000000000000000 '
b110 (
b0000000000000110 -
1/
#1800
0/
#1805
b0000000000000001 '
b0000000000000111 -
1/
#1810
0/
#1815
b0000000000000010 '
b0000000000001000 -
1/
#1820
0/
#1825
b0000000000000011 '
b0000000000001001 -
1/
#1830
0/
#1835
0#
b0000000000000100 '
b110 +
b0000000000000000 -
1/
#1840
0/
#1845
b0000000000000101 '
b0000000000000001 -
1/
#1850
0/
#1855
b0000000000000110 '
b0000000000000010 -
1/
#1860
0/
#1865
b0000000000000111 '
b0000000000000011 -
1/
#1870
0/
#1875
b0000000000001000 '
b0000000000000100 -
1/
#1880
0/
#1885
b0000000000001001 '
b0000000000000101 -
1/
#1890
0/
#1895
b0000000000000000 '
b111 (
b0000000000000110 -
1/
#1900
0/
#1905
b0000000000000001 '
b0000000000000111 -
1/
#1910
0/
#1915
b0000000000000010 '
b0000000000001000 -
1/
#1920
0/
#1925
b0000000000000011 '
b0000000000001001 -
1/
#1930
0/
#1935
b0000000000000100 '
b111 +
b0000000000000000 -
1/
#1940
0/
#1945
b0000000000000101 '
b0000000000000001 -
1/
#1950
0/
#1955
b0000000000000110 '
b0000000000000010 -
1/
#1960
0/
#1965
b0000000000000111 '
b0000000000000011 -
1/
#1970
0/
#1975
b0000000000001000 '
b0000000000000100 -
1/
#1980
0/
#1985
b0000000000001001 '
b0000000000000101 -
1/
#1990
0/
#1995
b0000000000000000 '
b000 (
b00111100 )
b11 *
b0000000000000110 -
1/
#2000
0/
#2005
b0000000000000001 '
b0000000000000111 -
1/
#2010
0/
#2015
b0000000000000010 '
b0000000000001000 -
1/
#2020
0/
#2025
b0000000000000011 '
b0000000000001001 -
1/
#2030
0/
#2035
1#
b0000000000000100 '
b0000000000000000 -
b11 .
1/
#2040
0/
#2045
b0000000000000101 '
b0000000000000001 -
1/
#2050
0/
#2055
b0000000000000110 '
b0000000000000010 -
1/
#2060
0/
#2065
b0000000000000111 '
b0000000000000011 -
1/
#2070
0/
#2075
b0000000000001000 '
b0000000000000100 -
1/
#2080
0/
#2085
b0000000000001001 '
b0000000000000101 -
1/
#2090
0/
#2095
b00111100 %
1&
b0000000000000000 '
b00 *
b0000000000000110 -
1/
#2100
0/
#2105
0&
b0000000000000111 -
1/
#2110
0/
#2115
b0000000000001000 -
1/
#2120
0/
#2125
b0000000000001001 -
1/
#2130
0/
#2135
0$
b0000000000000000 -
b00 .
1/
